LICENSE
pykomodefi/__init__.py
pykomodefi/models.py
pykomodefi-0.2.6.dist-info/LICENSE
pykomodefi-0.2.6.dist-info/METADATA
pykomodefi-0.2.6.dist-info/WHEEL
pykomodefi-0.2.6.dist-info/RECORD
