Metadata-Version: 2.1
Name: pykomodefi
Version: 0.2.6
Summary: A wrapper for the Komodo DeFi Framework API
Home-page: https://github.com/smk762/pykomodefi
License: MIT
Keywords: dex,crypto,komodo,defi,api,trading,atomic swaps
Author: smk
Author-email: smk@komodoplatform.com
Requires-Python: >=3.12,<4.0
Classifier: Environment :: Console
Classifier: Intended Audience :: Developers
Classifier: Intended Audience :: Financial and Insurance Industry
Classifier: License :: OSI Approved :: MIT License
Classifier: Natural Language :: English
Classifier: Operating System :: OS Independent
Classifier: Programming Language :: Python :: 3
Classifier: Programming Language :: Python :: 3.12
Classifier: Topic :: Software Development :: Libraries :: Python Modules
Requires-Dist: python-dotenv (>=1.1.0,<2.0.0)
Requires-Dist: requests (>=2.32.0,<3.0.0)
Project-URL: Documentation, https://github.com/smk762/pykomodefi
Project-URL: Repository, https://github.com/smk762/pykomodefi
